bgpfu/__init__.py
bgpfu/base.py
bgpfu/cli.py
bgpfu/client.py
bgpfu/io.py
bgpfu/irr/__init__.py
bgpfu/irr/base.py
bgpfu/irr/native.py
bgpfu/output.py
bgpfu/prefixlist/__init__.py
bgpfu/prefixlist/base.py
bgpfu/prefixlist/set.py
bgpfu/prefixlist/simple.py
bgpfu/roa.py
bgpfu/templates/cisco_ios.j2
bgpfu/templates/cisco_iox.j2
bgpfu/templates/juniper.j2
bgpfu-0.3.0.dist-info/entry_points.txt
bgpfu-0.3.0.dist-info/LICENSE
bgpfu-0.3.0.dist-info/WHEEL
bgpfu-0.3.0.dist-info/METADATA
bgpfu-0.3.0.dist-info/RECORD
